pystats_norm/__init__.py
pystats_norm/dnorm.py
pystats_norm/pnorm.py
pystats_norm/qnorm.py
pystats_norm/rnorm.py
pystats_norm-0.1.7.dist-info/LICENSE
pystats_norm-0.1.7.dist-info/METADATA
pystats_norm-0.1.7.dist-info/WHEEL
pystats_norm-0.1.7.dist-info/RECORD
