Metadata-Version: 2.3
Name: pystats_norm
Version: 0.1.7
Summary: A package for evaluating distributions in python
License: MIT
Author: Sarah Eshafi, Jason Lee, Abdul Safdar, Rong Wan
Requires-Python: >=3.11,<4.0
Classifier: License :: OSI Approved :: MIT License
Classifier: Programming Language :: Python :: 3
Classifier: Programming Language :: Python :: 3.11
Classifier: Programming Language :: Python :: 3.12
Classifier: Programming Language :: Python :: 3.13
Requires-Dist: colorama (>=0.4.6,<0.5.0)
Requires-Dist: numpy (>=2.2.1,<3.0.0)
Requires-Dist: pandas (>=2.2.3,<3.0.0)
Requires-Dist: scipy (>=1.15.1,<2.0.0)
